circular_protocol_api/__init__.py
circular_protocol_api/circular_exception.py
circular_protocol_api/circular_protocol_api.py
circular_protocol_api/helper.py
circular_protocol_api/nag_functions.py
circular_protocol_api-1.0.11.dist-info/licenses/LICENSE
circular_protocol_api-1.0.11.dist-info/METADATA
circular_protocol_api-1.0.11.dist-info/WHEEL
circular_protocol_api-1.0.11.dist-info/top_level.txt
circular_protocol_api-1.0.11.dist-info/RECORD
