Metadata-Version: 2.4
Name: circular_protocol_api
Version: 1.0.11
Summary: Circular Blockchain API written in Python 3
Home-page: https://github.com/circular-protocol/circular-py
Author: Danny De Novi
Author-email: Danny De Novi <dannydenovi29@gmail.com>
Project-URL: Homepage, https://github.com/circular-protocol/circular-py
Project-URL: Issues, https://github.com/circular-protocol/circular-py/issues
Classifier: Programming Language :: Python :: 3
Classifier: License :: OSI Approved :: MIT License
Classifier: Operating System :: OS Independent
Requires-Python: >=3.9
License-File: LICENSE
Requires-Dist: requests>=2.32.3
Requires-Dist: ecdsa>=0.19.0
Dynamic: author
Dynamic: home-page
Dynamic: license-file
Dynamic: requires-python
